{
  "images": [
    { "id": 1, "filename": "3bbl8l.jpg", "url": "https://files.catbox.moe/3bbl8l.jpg" },
    { "id": 2, "filename": "mmaggt.jpg", "url": "https://files.catbox.moe/mmaggt.jpg" },
    { "id": 3, "filename": "937w47.jpg", "url": "https://files.catbox.moe/937w47.jpg" },
    { "id": 4, "filename": "kkghnp.jpg", "url": "https://files.catbox.moe/kkghnp.jpg" },
    { "id": 5, "filename": "qbloc1.jpg", "url": "https://files.catbox.moe/qbloc1.jpg" },
    { "id": 6, "filename": "mhfhad.jpg", "url": "https://files.catbox.moe/mhfhad.jpg" },
    { "id": 7, "filename": "25hy35.jpg", "url": "https://files.catbox.moe/25hy35.jpg" },
    { "id": 8, "filename": "2d73wc.jpg", "url": "https://files.catbox.moe/2d73wc.jpg" },
    { "id": 9, "filename": "blrkvj.jpg", "url": "https://files.catbox.moe/blrkvj.jpg" },
    { "id": 10, "filename": "sjgoa7.jpg", "url": "https://files.catbox.moe/sjgoa7.jpg" },
    { "id": 11, "filename": "6p5jul.jpg", "url": "https://files.catbox.moe/6p5jul.jpg" },
    { "id": 12, "filename": "uq5sjk.jpg", "url": "https://files.catbox.moe/uq5sjk.jpg" },
    { "id": 13, "filename": "g4r9cw.jpg", "url": "https://files.catbox.moe/g4r9cw.jpg" }
  ]
}
